[{"class_name": "gate", "pointlist": [[274, 374], [240, 374], [237, 392], [276, 392]], "used": false}, {"class_name": "gate", "pointlist": [[274, 267], [272, 265], [242, 265], [240, 267]], "used": false}, {"class_name": "gate", "pointlist": [[290, 482], [225, 482], [221, 510], [294, 510]], "used": false}, {"class_name": "gate", "pointlist": [[315, 308], [201, 308], [160, 348], [359, 348]], "used": false}, {"class_name": "gate", "pointlist": [[280, 264], [233, 264], [228, 267], [285, 267]], "used": false}]